__init__.py
llm_min/__init__.py
llm_min/compacter.py
llm_min/crawler.py
llm_min/generator.py
llm_min/main.py
llm_min/search.py
llm_min/utils.py
llm_min/assets/__init__.py
llm_min/assets/llm_min_guideline.md
llm_min/llm/__init__.py
llm_min/llm/gemini.py
llm_min-0.3.1.dist-info/licenses/LICENSE
llm_min-0.3.1.dist-info/METADATA
llm_min-0.3.1.dist-info/WHEEL
llm_min-0.3.1.dist-info/entry_points.txt
llm_min-0.3.1.dist-info/top_level.txt
llm_min-0.3.1.dist-info/RECORD
