Metadata-Version: 2.4
Name: llm-min
Version: 0.3.1
Summary: Generates LLM context by scraping and summarizing documentation for Python libraries listed in a requirements.txt file.
Author-email: marv1nnnnn <marvin1996325@gmail.com>
License: MIT License
Project-URL: Repository, https://github.com/marvin1996325/llm-min
Keywords: llm,documentation,scraping,summarization,python,pypi
Classifier: Development Status :: 3 - Alpha
Classifier: Intended Audience :: Developers
Classifier: Topic :: Software Development :: Documentation
Classifier: Topic :: Text Processing :: Indexing
Classifier: License :: OSI Approved :: MIT License
Classifier: Programming Language :: Python :: 3
Classifier: Programming Language :: Python :: 3.10
Classifier: Programming Language :: Python :: 3.11
Classifier: Programming Language :: Python :: 3.12
Requires-Python: >=3.10
License-File: LICENSE
Requires-Dist: crawl4ai>=0.6.2
Requires-Dist: httpx>=0.27.0
Requires-Dist: beautifulsoup4>=4.12.3
Requires-Dist: lxml>=5.2.1
Requires-Dist: google-genai>=1.0.0
Requires-Dist: duckduckgo_search>=5.3.1b1
Requires-Dist: pydantic>=2.11.3
Requires-Dist: typer>=0.12.3
Requires-Dist: toml>=0.10.2
Requires-Dist: tiktoken>=0.9.0
Provides-Extra: dev
Requires-Dist: pytest>=8.0; extra == "dev"
Requires-Dist: pytest-asyncio; extra == "dev"
Requires-Dist: ruff>=0.4.0; extra == "dev"
Requires-Dist: build>=1.0; extra == "dev"
Dynamic: license-file
